eruhttp
