Metadata-Version: 1.0
Name: eru-py
Version: 0.0.25
Summary: ERU client for python
Home-page: UNKNOWN
Author: tonic
Author-email: tonic@wolege.ca
License: UNKNOWN
Platform: UNKNOWN
